BitMask/__init__.py
BitMask/bitmask_module.py
bitmaskfunctionalties-1.1.0.dist-info/METADATA
bitmaskfunctionalties-1.1.0.dist-info/WHEEL
bitmaskfunctionalties-1.1.0.dist-info/licenses/LICENSE.txt
bitmaskfunctionalties-1.1.0.dist-info/RECORD
